robusta_cli/__init__.py
robusta_cli/_version.py
robusta_cli/auth.py
robusta_cli/backend_profile.py
robusta_cli/demo_alert.py
robusta_cli/eula.py
robusta_cli/integrations_cmd.py
robusta_cli/main.py
robusta_cli/playbooks_cmd.py
robusta_cli/self_host.py
robusta_cli/simple_sink_config.py
robusta_cli/slack_feedback_message.py
robusta_cli/slack_verification.py
robusta_cli/utils.py
robusta_cli-1.1.dist-info/LICENSE
robusta_cli-1.1.dist-info/METADATA
robusta_cli-1.1.dist-info/WHEEL
robusta_cli-1.1.dist-info/entry_points.txt
robusta_cli-1.1.dist-info/RECORD
